{"0": {}, "1": {"Age": "69", "Total Assets": "Rs\u00a040,16,707 ~ 40\u00a0Lacs+", "Candidate": {"data": "Mostafa Bin Quasem\u00a0\u00a0 Winner", "url": "http://myneta.info/westbengal2011/candidate.php?candidate_id=631"}, "Education": "Post Graduate", "Liabilities": "Rs\u00a00 ~", "Criminal Cases": "0", "Party": "CPM"}, "2": {"Age": "32", "Total Assets": "Rs\u00a01,30,000 ~ 1\u00a0Lacs+", "Candidate": {"data": "Anwar Hossain Molla", "url": "http://myneta.info/westbengal2011/candidate.php?candidate_id=1619"}, "Education": "8th Pass", "Liabilities": "Rs\u00a00 ~", "Criminal Cases": "0", "Party": "AIMF"}, "3": {"Age": "34", "Total Assets": "Rs\u00a03,02,088 ~ 3\u00a0Lacs+", "Candidate": {"data": "Prosanta Biswas", "url": "http://myneta.info/westbengal2011/candidate.php?candidate_id=819"}, "Education": "Graduate", "Liabilities": "Rs\u00a01,60,000 ~ 1\u00a0Lacs+", "Criminal Cases": "0", "Party": "BSP"}, "4": {"Age": "40", "Total Assets": "Rs\u00a07,41,262 ~ 7\u00a0Lacs+", "Candidate": {"data": "Rafikul Mandal", "url": "http://myneta.info/westbengal2011/candidate.php?candidate_id=1618"}, "Education": "Others", "Liabilities": "Rs\u00a00 ~", "Criminal Cases": "0", "Party": "PDCI"}, "5": {"Age": "68", "Total Assets": "Rs\u00a055,01,138 ~ 55\u00a0Lacs+", "Candidate": {"data": "Sardar Amjad Ali", "url": "http://myneta.info/westbengal2011/candidate.php?candidate_id=632"}, "Education": "Graduate Professional", "Liabilities": "Rs\u00a00 ~", "Criminal Cases": "0", "Party": "AITC"}, "6": {"Age": "40", "Total Assets": "Rs\u00a02,15,389 ~ 2\u00a0Lacs+", "Candidate": {"data": "Soumen Mandal", "url": "http://myneta.info/westbengal2011/candidate.php?candidate_id=633"}, "Education": "Graduate", "Liabilities": "Rs\u00a00 ~", "Criminal Cases": "1", "Party": "BJP"}}