{"0": {}, "1": {"Age": "62", "Total Assets": "Rs\u00a018,33,873 ~ 18\u00a0Lacs+", "Candidate": {"data": "Dr. Surjya Kanta Mishra\u00a0\u00a0 Winner", "url": "http://myneta.info/westbengal2011/candidate.php?candidate_id=1084"}, "Education": "Graduate Professional", "Liabilities": "Rs\u00a00 ~", "Criminal Cases": "0", "Party": "CPM"}, "2": {"Age": "50", "Total Assets": "Rs\u00a011,49,000 ~ 11\u00a0Lacs+", "Candidate": {"data": "Krishna Prasad Roy", "url": "http://myneta.info/westbengal2011/candidate.php?candidate_id=1082"}, "Education": "12th Pass", "Liabilities": "Rs\u00a01,23,000 ~ 1\u00a0Lacs+", "Criminal Cases": "0", "Party": "BJP"}, "3": {"Age": "47", "Total Assets": "Rs\u00a07,79,160 ~ 7\u00a0Lacs+", "Candidate": {"data": "Surja Kanta Atta", "url": "http://myneta.info/westbengal2011/candidate.php?candidate_id=1083"}, "Education": "12th Pass", "Liabilities": "Rs\u00a05,74,000 ~ 5\u00a0Lacs+", "Criminal Cases": "10", "Party": "AITC"}}