{"0": {}, "1": {"Age": "65", "Total Assets": "Rs\u00a043,50,000 ~ 43\u00a0Lacs+", "Candidate": {"data": "Bharati Tamang", "url": "http://myneta.info/westbengal2011/candidate.php?candidate_id=148"}, "Education": "Graduate", "Liabilities": "Rs\u00a08,40,000 ~ 8\u00a0Lacs+", "Criminal Cases": "0", "Party": "Akhil Bharatiya Gorkha League"}, "2": {"Age": "65", "Total Assets": "Rs\u00a05,66,212 ~ 5\u00a0Lacs+", "Candidate": {"data": "Bim Subba", "url": "http://myneta.info/westbengal2011/candidate.php?candidate_id=149"}, "Education": "8th Pass", "Liabilities": "Rs\u00a010,683 ~ 10\u00a0Thou+", "Criminal Cases": "0", "Party": "GNLF"}, "3": {"Age": "56", "Total Assets": "Rs\u00a067,47,034 ~ 67\u00a0Lacs+", "Candidate": {"data": "K. B. Wattar", "url": "http://myneta.info/westbengal2011/candidate.php?candidate_id=54"}, "Education": "12th Pass", "Liabilities": "Rs\u00a024,090 ~ 24\u00a0Thou+", "Criminal Cases": "0", "Party": "CPM"}, "4": {"Age": "55", "Total Assets": "Rs\u00a018,68,923 ~ 18\u00a0Lacs+", "Candidate": {"data": "Nahakul Chandra Chhetri", "url": "http://myneta.info/westbengal2011/candidate.php?candidate_id=53"}, "Education": "Graduate", "Liabilities": "Rs\u00a00 ~", "Criminal Cases": "0", "Party": "INC"}}