{"0": {}, "1": {"Age": "63", "Total Assets": "Rs\u00a044,98,455 ~ 44\u00a0Lacs+", "Candidate": {"data": "Chowdhury Md Hedayatullah\u00a0\u00a0 Winner", "url": "http://myneta.info/westbengal2011/candidate.php?candidate_id=1045"}, "Education": "Graduate", "Liabilities": "Rs\u00a08,00,000 ~ 8\u00a0Lacs+", "Criminal Cases": "0", "Party": "CPM"}, "2": {"Age": "41", "Total Assets": "Rs\u00a01,81,63,830 ~ 1\u00a0Crore+", "Candidate": {"data": "Abdul Kased Shaikh(Khokon Bhai)", "url": "http://myneta.info/westbengal2011/candidate.php?candidate_id=1323"}, "Education": "8th Pass", "Liabilities": "Rs\u00a010,13,538 ~ 10\u00a0Lacs+", "Criminal Cases": "0", "Party": "PDCI"}, "3": {"Age": "67", "Total Assets": "Rs\u00a019,32,162 ~ 19\u00a0Lacs+", "Candidate": {"data": "Abu Ayes Mondal", "url": "http://myneta.info/westbengal2011/candidate.php?candidate_id=1044"}, "Education": "Graduate", "Liabilities": "Rs\u00a00 ~", "Criminal Cases": "0", "Party": "AITC"}, "4": {"Age": "65", "Total Assets": "Rs\u00a010,66,000 ~ 10\u00a0Lacs+", "Candidate": {"data": "Annada Prasad Bhattachoryya", "url": "http://myneta.info/westbengal2011/candidate.php?candidate_id=1389"}, "Education": "Post Graduate", "Liabilities": "Rs\u00a00 ~", "Criminal Cases": "1", "Party": "CPI(ML)(L)"}, "5": {"Age": "45", "Total Assets": "Rs\u00a012,30,000 ~ 12\u00a0Lacs+", "Candidate": {"data": "Sakshi Gopal Ghosh", "url": "http://myneta.info/westbengal2011/candidate.php?candidate_id=1046"}, "Education": "10th Pass", "Liabilities": "Rs\u00a00 ~", "Criminal Cases": "2", "Party": "BJP"}, "6": {"Age": "50", "Total Assets": "Rs\u00a09,700 ~ 9\u00a0Thou+", "Candidate": {"data": "Sukumar Das", "url": "http://myneta.info/westbengal2011/candidate.php?candidate_id=1047"}, "Education": "8th Pass", "Liabilities": "Rs\u00a0500 ~ 5\u00a0Hund+", "Criminal Cases": "1", "Party": "BSP"}, "7": {"Age": "26", "Total Assets": "Rs\u00a01,626 ~ 1\u00a0Thou+", "Candidate": {"data": "Sunil Soren", "url": "http://myneta.info/westbengal2011/candidate.php?candidate_id=1388"}, "Education": "8th Pass", "Liabilities": "Rs\u00a00 ~", "Criminal Cases": "0", "Party": "JDP"}}