{"0": {}, "1": {"Age": "62", "Total Assets": "Rs\u00a01,82,284 ~ 1\u00a0Lacs+", "Candidate": {"data": "Ashok Kumar Deb\u00a0\u00a0 Winner", "url": "http://myneta.info/westbengal2011/candidate.php?candidate_id=714"}, "Education": "Graduate Professional", "Liabilities": "Rs\u00a00 ~", "Criminal Cases": "1", "Party": "AITC"}, "2": {"Age": "50", "Total Assets": "Rs\u00a088,02,050 ~ 88\u00a0Lacs+", "Candidate": {"data": "Ariful Islam", "url": "http://myneta.info/westbengal2011/candidate.php?candidate_id=713"}, "Education": "Graduate", "Liabilities": "Rs\u00a012,00,000 ~ 12\u00a0Lacs+", "Criminal Cases": "0", "Party": "BJP"}, "3": {"Age": "46", "Total Assets": "Rs\u00a08,45,210 ~ 8\u00a0Lacs+", "Candidate": {"data": "Hrishikesh Podder", "url": "http://myneta.info/westbengal2011/candidate.php?candidate_id=712"}, "Education": "10th Pass", "Liabilities": "Rs\u00a075,000 ~ 75\u00a0Thou+", "Criminal Cases": "0", "Party": "CPM"}, "4": {"Age": "40", "Total Assets": "Rs\u00a044,000 ~ 44\u00a0Thou+", "Candidate": {"data": "Maloy Santra", "url": "http://myneta.info/westbengal2011/candidate.php?candidate_id=1736"}, "Education": "Graduate", "Liabilities": "Rs\u00a00 ~", "Criminal Cases": "0", "Party": "IND"}, "5": {"Age": "36", "Total Assets": "Rs\u00a091,000 ~ 91\u00a0Thou+", "Candidate": {"data": "Mukunda Patla", "url": "http://myneta.info/westbengal2011/candidate.php?candidate_id=836"}, "Education": "10th Pass", "Liabilities": "Rs\u00a00 ~", "Criminal Cases": "0", "Party": "BSP"}, "6": {"Age": "58", "Total Assets": "Rs\u00a013,35,000 ~ 13\u00a0Lacs+", "Candidate": {"data": "Shyama Prasad Santra", "url": "http://myneta.info/westbengal2011/candidate.php?candidate_id=1734"}, "Education": "Post Graduate", "Liabilities": "Rs\u00a00 ~", "Criminal Cases": "0", "Party": "IND"}, "7": {"Age": "31", "Total Assets": "Rs\u00a01,05,000 ~ 1\u00a0Lacs+", "Candidate": {"data": "Sk. Basir Ali", "url": "http://myneta.info/westbengal2011/candidate.php?candidate_id=1735"}, "Education": "Graduate", "Liabilities": "Rs\u00a00 ~", "Criminal Cases": "0", "Party": "IUC"}}