{"0": {}, "1": {"Education": "Graduate", "Liabilities": "Rs\u00a00 ~", "Criminal Cases": "0", "Party": "AITC", "Total Assets": "Rs\u00a06,68,504 ~ 6\u00a0Lacs+", "Age": "33", "Candidate": {"url": "http://myneta.info/westbengal2016/candidate.php?candidate_id=932", "data": "Alok Kumar Majhi\u00a0\u00a0 Winner"}}, "2": {"Education": "12th Pass", "Liabilities": "Rs\u00a04,47,959 ~ 4\u00a0Lacs+", "Criminal Cases": "0", "Party": "AIFB", "Total Assets": "Rs\u00a010,11,773 ~ 10\u00a0Lacs+", "Age": "64", "Candidate": {"url": "http://myneta.info/westbengal2016/candidate.php?candidate_id=931", "data": "Nandalal Pondit"}}, "3": {"Education": "Graduate", "Liabilities": "Rs\u00a00 ~", "Criminal Cases": "0", "Party": "BJP", "Total Assets": "Rs\u00a07,36,900 ~ 7\u00a0Lacs+", "Age": "53", "Candidate": {"url": "http://myneta.info/westbengal2016/candidate.php?candidate_id=933", "data": "Sundar Paswan"}}}