{"0": {}, "1": {"Education": "Doctorate", "Liabilities": "Rs\u00a00 ~", "Criminal Cases": "0", "Party": "AITC", "Total Assets": "Rs\u00a055,64,979 ~ 55\u00a0Lacs+", "Age": "75", "Candidate": {"url": "http://myneta.info/westbengal2016/candidate.php?candidate_id=861", "data": "Rabiranjan Chattopadhyay\u00a0\u00a0 Winner"}}, "2": {"Education": "Post Graduate", "Liabilities": "Rs\u00a05,06,164 ~ 5\u00a0Lacs+", "Criminal Cases": "5", "Party": "CPI(M)", "Total Assets": "Rs\u00a021,89,895 ~ 21\u00a0Lacs+", "Age": "57", "Candidate": {"url": "http://myneta.info/westbengal2016/candidate.php?candidate_id=857", "data": "Ainul Haque"}}, "3": {"Education": "8th Pass", "Liabilities": "Rs\u00a00 ~", "Criminal Cases": "0", "Party": "BSP", "Total Assets": "Rs\u00a011,500 ~ 11\u00a0Thou+", "Age": "46", "Candidate": {"url": "http://myneta.info/westbengal2016/candidate.php?candidate_id=862", "data": "Md. Harun"}}, "4": {"Education": "12th Pass", "Liabilities": "Rs\u00a00 ~", "Criminal Cases": "0", "Party": "SUCI(C)", "Total Assets": "Rs\u00a03,78,822 ~ 3\u00a0Lacs+", "Age": "42", "Candidate": {"url": "http://myneta.info/westbengal2016/candidate.php?candidate_id=859", "data": "Parikshit Gorain"}}, "5": {"Education": "Others", "Liabilities": "Rs\u00a00 ~", "Criminal Cases": "0", "Party": "BJP", "Total Assets": "Rs\u00a05,35,000 ~ 5\u00a0Lacs+", "Age": "50", "Candidate": {"url": "http://myneta.info/westbengal2016/candidate.php?candidate_id=858", "data": "Prabal Roy"}}, "6": {"Education": "Graduate Professional", "Liabilities": "Rs\u00a00 ~", "Criminal Cases": "0", "Party": "IND", "Total Assets": "Rs\u00a018,14,970 ~ 18\u00a0Lacs+", "Age": "63", "Candidate": {"url": "http://myneta.info/westbengal2016/candidate.php?candidate_id=860", "data": "Samir Kumar Roy"}}}