{"0": {}, "1": {"Candidate": {"data": "Rabiranjan Chattopadhyay\u00a0\u00a0 Winner", "url": "http://myneta.info/westbengal2016/candidate.php?candidate_id=861"}, "Party": "AITC", "Criminal Cases": "0", "Education": "Doctorate", "Age": "75", "Total Assets": "Rs\u00a055,64,979 ~ 55\u00a0Lacs+", "Liabilities": "Rs\u00a00 ~"}, "2": {"Candidate": {"data": "Ainul Haque", "url": "http://myneta.info/westbengal2016/candidate.php?candidate_id=857"}, "Party": "CPI(M)", "Criminal Cases": "5", "Education": "Post Graduate", "Age": "57", "Total Assets": "Rs\u00a021,89,895 ~ 21\u00a0Lacs+", "Liabilities": "Rs\u00a05,06,164 ~ 5\u00a0Lacs+"}, "3": {"Candidate": {"data": "Md. Harun", "url": "http://myneta.info/westbengal2016/candidate.php?candidate_id=862"}, "Party": "BSP", "Criminal Cases": "0", "Education": "8th Pass", "Age": "46", "Total Assets": "Rs\u00a011,500 ~ 11\u00a0Thou+", "Liabilities": "Rs\u00a00 ~"}, "4": {"Candidate": {"data": "Parikshit Gorain", "url": "http://myneta.info/westbengal2016/candidate.php?candidate_id=859"}, "Party": "SUCI(C)", "Criminal Cases": "0", "Education": "12th Pass", "Age": "42", "Total Assets": "Rs\u00a03,78,822 ~ 3\u00a0Lacs+", "Liabilities": "Rs\u00a00 ~"}, "5": {"Candidate": {"data": "Prabal Roy", "url": "http://myneta.info/westbengal2016/candidate.php?candidate_id=858"}, "Party": "BJP", "Criminal Cases": "0", "Education": "Others", "Age": "50", "Total Assets": "Rs\u00a05,35,000 ~ 5\u00a0Lacs+", "Liabilities": "Rs\u00a00 ~"}, "6": {"Candidate": {"data": "Samir Kumar Roy", "url": "http://myneta.info/westbengal2016/candidate.php?candidate_id=860"}, "Party": "IND", "Criminal Cases": "0", "Education": "Graduate Professional", "Age": "63", "Total Assets": "Rs\u00a018,14,970 ~ 18\u00a0Lacs+", "Liabilities": "Rs\u00a00 ~"}}