{"0": {}, "1": {"Education": "Graduate", "Liabilities": "Rs\u00a00 ~", "Criminal Cases": "0", "Party": "AITC", "Total Assets": "Rs\u00a031,34,794 ~ 31\u00a0Lacs+", "Age": "60", "Candidate": {"url": "http://myneta.info/westbengal2016/candidate.php?candidate_id=4", "data": "Arup Kumar Khan\u00a0\u00a0 Winner"}}, "2": {"Education": "8th Pass", "Liabilities": "Rs\u00a00 ~", "Criminal Cases": "2", "Party": "BJP", "Total Assets": "Rs\u00a06,72,889 ~ 6\u00a0Lacs+", "Age": "52", "Candidate": {"url": "http://myneta.info/westbengal2016/candidate.php?candidate_id=246", "data": "Amarnath Shaka"}}, "3": {"Education": "Graduate Professional", "Liabilities": "Rs\u00a060,000 ~ 60\u00a0Thou+", "Criminal Cases": "0", "Party": "IND", "Total Assets": "Rs\u00a05,58,000 ~ 5\u00a0Lacs+", "Age": "60", "Candidate": {"url": "http://myneta.info/westbengal2016/candidate.php?candidate_id=156", "data": "Ashoke Chattopadhyay"}}, "4": {"Education": "8th Pass", "Liabilities": "Rs\u00a00 ~", "Criminal Cases": "0", "Party": "CPI(ML)(L)", "Total Assets": "Rs\u00a09,65,200 ~ 9\u00a0Lacs+", "Age": "56", "Candidate": {"url": "http://myneta.info/westbengal2016/candidate.php?candidate_id=158", "data": "Baidyanath China"}}, "5": {"Education": "10th Pass", "Liabilities": "Rs\u00a00 ~", "Criminal Cases": "0", "Party": "AIFB", "Total Assets": "Rs\u00a01,31,652 ~ 1\u00a0Lacs+", "Age": "59", "Candidate": {"url": "http://myneta.info/westbengal2016/candidate.php?candidate_id=247", "data": "Manik Mukherjee"}}, "6": {"Education": "Post Graduate", "Liabilities": "Rs\u00a00 ~", "Criminal Cases": "0", "Party": "SUCI(C)", "Total Assets": "Rs\u00a011,300 ~ 11\u00a0Thou+", "Age": "33", "Candidate": {"url": "http://myneta.info/westbengal2016/candidate.php?candidate_id=157", "data": "Sabiruddin Bhuina"}}, "7": {"Education": "10th Pass", "Liabilities": "Rs\u00a00 ~", "Criminal Cases": "0", "Party": "BSP", "Total Assets": "Rs\u00a0500 ~ 5\u00a0Hund+", "Age": "30", "Candidate": {"url": "http://myneta.info/westbengal2016/candidate.php?candidate_id=248", "data": "Sadhan Chattaraj"}}}