{"1": {"Name": {"data": "Bikash Hazra", "url": "http://www.myneta.info/ls2014/http://myneta.info/ls2014/candidate.php?candidate_id=9782"}, "Age": "50", "Gender": "M", "Party Code": "Bahujan Mukti Party", "Criminal Cases": "No", "Number of Cases": "0", "Serious IPC Counts": "0", "IPC Details*": "NaN", "Education Level": "8th Pass", "Movable Assets": "1,37,500~ 1\u00a0Lacs+", "Immovable Assets": "26,00,000~ 26\u00a0Lacs+", "Total Assets": "27,37,500~ 27\u00a0Lacs+", "Total Liabilities": "0~", "PAN Given(Y or N)": "N"}, "2": {"Name": {"data": "Dr. Kakali Ghoshdostidar", "url": "http://www.myneta.info/ls2014/http://myneta.info/ls2014/candidate.php?candidate_id=9318"}, "Age": "55", "Gender": "F", "Party Code": "AITC", "Criminal Cases": "No", "Number of Cases": "0", "Serious IPC Counts": "0", "IPC Details*": "NaN", "Education Level": "Graduate Professional", "Movable Assets": "1,40,54,311~ 1\u00a0Crore+", "Immovable Assets": "1,72,00,000~ 1\u00a0Crore+", "Total Assets": "3,12,54,311~ 3\u00a0Crore+", "Total Liabilities": "11,68,220~ 11\u00a0Lacs+", "PAN Given(Y or N)": "Y"}, "3": {"Name": {"data": "Dr. Mortoza Hossain", "url": "http://www.myneta.info/ls2014/http://myneta.info/ls2014/candidate.php?candidate_id=9322"}, "Age": "69", "Gender": "M", "Party Code": "AIFB", "Criminal Cases": "No", "Number of Cases": "0", "Serious IPC Counts": "0", "IPC Details*": "NaN", "Education Level": "Graduate Professional", "Movable Assets": "81,69,803~ 81\u00a0Lacs+", "Immovable Assets": "1,21,00,000~ 1\u00a0Crore+", "Total Assets": "2,02,69,803~ 2\u00a0Crore+", "Total Liabilities": "16,50,000~ 16\u00a0Lacs+", "PAN Given(Y or N)": "Y"}, "4": {"Name": {"data": "Kalyan Basak", "url": "http://www.myneta.info/ls2014/http://myneta.info/ls2014/candidate.php?candidate_id=9326"}, "Age": "37", "Gender": "M", "Party Code": "IND", "Criminal Cases": "Yes", "Number of Cases": "1", "Serious IPC Counts": "0", "IPC Details*": "NaN", "Education Level": "12th Pass", "Movable Assets": "3,26,359~ 3\u00a0Lacs+", "Immovable Assets": "37,00,000~ 37\u00a0Lacs+", "Total Assets": "40,26,359~ 40\u00a0Lacs+", "Total Liabilities": "3,90,000~ 3\u00a0Lacs+", "PAN Given(Y or N)": "Y"}, "5": {"Name": {"data": "Md. Rafikul Islam", "url": "http://www.myneta.info/ls2014/http://myneta.info/ls2014/candidate.php?candidate_id=9320"}, "Age": "38", "Gender": "M", "Party Code": "Welfare Party of India", "Criminal Cases": "No", "Number of Cases": "0", "Serious IPC Counts": "0", "IPC Details*": "NaN", "Education Level": "Post Graduate", "Movable Assets": "1,28,000~ 1\u00a0Lacs+", "Immovable Assets": "1,50,000~ 1\u00a0Lacs+", "Total Assets": "2,78,000~ 2\u00a0Lacs+", "Total Liabilities": "0~", "PAN Given(Y or N)": "Y"}, "6": {"Name": {"data": "Morttaja Hosen", "url": "http://www.myneta.info/ls2014/http://myneta.info/ls2014/candidate.php?candidate_id=9780"}, "Age": "32", "Gender": "M", "Party Code": "IND", "Criminal Cases": "No", "Number of Cases": "0", "Serious IPC Counts": "0", "IPC Details*": "NaN", "Education Level": "Graduate", "Movable Assets": "32,500~ 32\u00a0Thou+", "Immovable Assets": "0~", "Total Assets": "32,500~ 32\u00a0Thou+", "Total Liabilities": "0~", "PAN Given(Y or N)": "Y"}, "7": {"Name": {"data": "P.C. Sorkar Junior", "url": "http://www.myneta.info/ls2014/http://myneta.info/ls2014/candidate.php?candidate_id=9321"}, "Age": "66", "Gender": "M", "Party Code": "BJP", "Criminal Cases": "Yes", "Number of Cases": "1", "Serious IPC Counts": "1", "IPC Details*": "Assault or criminal force to woman with intent to outrage her modesty(354), Word, gesture or act intended to insult the modesty of a woman(509),", "Education Level": "Doctorate", "Movable Assets": "1,94,65,063~ 1\u00a0Crore+", "Immovable Assets": "3,49,51,750~ 3\u00a0Crore+", "Total Assets": "5,44,16,813~ 5\u00a0Crore+", "Total Liabilities": "15,36,534~ 15\u00a0Lacs+", "PAN Given(Y or N)": "Y"}, "8": {"Name": {"data": "Paresh Chandra Ghosh", "url": "http://www.myneta.info/ls2014/http://myneta.info/ls2014/candidate.php?candidate_id=9319"}, "Age": "58", "Gender": "M", "Party Code": "SUCI(C)", "Criminal Cases": "No", "Number of Cases": "0", "Serious IPC Counts": "0", "IPC Details*": "NaN", "Education Level": "Post Graduate", "Movable Assets": "32,200~ 32\u00a0Thou+", "Immovable Assets": "7,00,000~ 7\u00a0Lacs+", "Total Assets": "7,32,200~ 7\u00a0Lacs+", "Total Liabilities": "10,00,000~ 10\u00a0Lacs+", "PAN Given(Y or N)": "Y"}, "9": {"Name": {"data": "Riju Ghosal", "url": "http://www.myneta.info/ls2014/http://myneta.info/ls2014/candidate.php?candidate_id=9324"}, "Age": "39", "Gender": "M", "Party Code": "INC", "Criminal Cases": "No", "Number of Cases": "0", "Serious IPC Counts": "0", "IPC Details*": "NaN", "Education Level": "Post Graduate", "Movable Assets": "2,02,23,157~ 2\u00a0Crore+", "Immovable Assets": "90,00,000~ 90\u00a0Lacs+", "Total Assets": "2,92,23,157~ 2\u00a0Crore+", "Total Liabilities": "5,00,000~ 5\u00a0Lacs+", "PAN Given(Y or N)": "Y"}, "10": {"Name": {"data": "Shri Kaushik Das Gupta", "url": "http://www.myneta.info/ls2014/http://myneta.info/ls2014/candidate.php?candidate_id=9781"}, "Age": "47", "Gender": "M", "Party Code": "IND", "Criminal Cases": "No", "Number of Cases": "0", "Serious IPC Counts": "0", "IPC Details*": "NaN", "Education Level": "Graduate", "Movable Assets": "74,000~ 74\u00a0Thou+", "Immovable Assets": "0~", "Total Assets": "74,000~ 74\u00a0Thou+", "Total Liabilities": "0~", "PAN Given(Y or N)": "Y"}, "11": {"Name": {"data": "Sukla Bhuimali", "url": "http://www.myneta.info/ls2014/http://myneta.info/ls2014/candidate.php?candidate_id=9783"}, "Age": "32", "Gender": "F", "Party Code": "CPI(ML) Red Star", "Criminal Cases": "No", "Number of Cases": "0", "Serious IPC Counts": "0", "IPC Details*": "NaN", "Education Level": "Post Graduate", "Movable Assets": "1,300~ 1\u00a0Thou+", "Immovable Assets": "0~", "Total Assets": "1,300~ 1\u00a0Thou+", "Total Liabilities": "0~", "PAN Given(Y or N)": "N"}, "12": {"Name": {"data": "Sukumar Bala", "url": "http://www.myneta.info/ls2014/http://myneta.info/ls2014/candidate.php?candidate_id=9323"}, "Age": "39", "Gender": "M", "Party Code": "BSP", "Criminal Cases": "No", "Number of Cases": "0", "Serious IPC Counts": "0", "IPC Details*": "NaN", "Education Level": "Post Graduate", "Movable Assets": "11,38,552~ 11\u00a0Lacs+", "Immovable Assets": "27,50,000~ 27\u00a0Lacs+", "Total Assets": "38,88,552~ 38\u00a0Lacs+", "Total Liabilities": "6,50,000~ 6\u00a0Lacs+", "PAN Given(Y or N)": "Y"}}