{"0": {"dependent2": "Nil", "dependent1": "Nil", "self": "Nil", "dependent3": "Nil", "Description": "Agricultural Land", "spouse": "Nil"}, "1": {"dependent2": "Nil", "dependent1": "Nil", "self": "Touzi No.1 Mouza 121 Kechuadanga Kh.Rs 1975, Dag No.4460,4479\nTotal Area 1089 sq.ft  \nBuilt Up Area  \nWhether Inherited N \nPurchase Date 2009-06-16 \nPurchase Cost 22335.00 \nDevelopment Cost 0.00 1,00,000\u00a0\u00a01\u00a0Lacs+", "dependent3": "Nil", "Description": "Non Agricultural Land", "spouse": "Nil"}, "2": {"dependent2": "Nil", "dependent1": "Nil", "self": "Nil", "dependent3": "Nil", "Description": "Commercial Buildings", "spouse": "Nil"}, "3": {"dependent2": "Nil", "dependent1": "Nil", "self": "Touzi No.1 Mouza Kechuantanga Kh.No.1759 Dag No.4479 P.S. Murutia Nadia \nTotal Area 2613 sq.ft  \nBuilt Up Area 800 sq.ft  \nWhether Inherited N \nPurchase Date 2003-06-06 \nPurchase Cost 39600.00 \nDevelopment Cost 300000.00 4,00,000\u00a0\u00a04\u00a0Lacs+", "dependent3": "Nil", "Description": "Residential Buildings", "spouse": "Nil"}, "4": {"dependent2": "Nil", "dependent1": "Nil", "self": "Nil", "dependent3": "Nil", "Description": "Others", "spouse": "Nil"}, "5": {"dependent2": "Nil", "dependent1": "Nil", "self": "5,00,000\u00a0\u00a05\u00a0Lacs+", "dependent3": "Nil", "Description": "Total Current Market Value of (i) to (v) (as per Affidavit)", "spouse": "Nil"}, "6": {"dependent2": "Nil", "dependent1": "Nil", "self": "Rs\u00a05,00,000 5\u00a0Lacs+", "dependent3": "Nil", "Description": "Totals Calculated", "spouse": "Nil"}}