{"0": {"dependent2": "Nil", "dependent3": "Nil", "Description": "Agricultural Land", "spouse": "Nil", "self": "Chapra 39\nTotal Area 0.33 Acre \nBuilt Up Area  \nWhether Inherited Y \nPurchase Date 0000-00-00 \nPurchase Cost 0.00 \nDevelopment Cost 0.00 3,00,000\u00a0\u00a03\u00a0Lacs+ Chapra 39\nTotal Area 0.11 Acre \nBuilt Up Area  \nWhether Inherited Y \nPurchase Date 0000-00-00 \nPurchase Cost 0.00 \nDevelopment Cost 0.00 1,00,000\u00a0\u00a01\u00a0Lacs+ Chapra 39\nTotal Area 0.33 Acre \nBuilt Up Area  \nWhether Inherited Y \nPurchase Date 0000-00-00 \nPurchase Cost 0.00 \nDevelopment Cost 0.00 3,00,000\u00a0\u00a03\u00a0Lacs+ Chapra 38 (jointly)\nTotal Area 0.29 Acre \nBuilt Up Area  \nWhether Inherited N \nPurchase Date 2012-02-10 \nPurchase Cost 71891.00 \nDevelopment Cost 0.00 2,90,000\u00a0\u00a02\u00a0Lacs+ Chapra 39\r\n\nTotal Area 0.19 Acre \nBuilt Up Area  \nWhether Inherited N \nPurchase Date 2014-06-11 \nPurchase Cost 1341888.00 \nDevelopment Cost 0.00 20,00,000\u00a0\u00a020\u00a0Lacs+ Chapra 39\r\n\nTotal Area 1.76 Acre \nBuilt Up Area  \nWhether Inherited N \nPurchase Date 2014-03-26 \nPurchase Cost 2473858.00 \nDevelopment Cost 0.00 25,00,000\u00a0\u00a025\u00a0Lacs+ Chapra 38 (jointly)\r\n\nTotal Area 0.19 Acre \nBuilt Up Area  \nWhether Inherited N \nPurchase Date 2012-08-01 \nPurchase Cost 62700.00 \nDevelopment Cost 0.00 1,20,000\u00a0\u00a01\u00a0Lacs+", "dependent1": "Nil", "Sr No": "i"}, "1": {"dependent2": "Nil", "dependent3": "Nil", "Description": "Non Agricultural Land", "spouse": "Nil", "self": "Bangaljhi 33\nTotal Area 2616 sqft \nBuilt Up Area  \nWhether Inherited N \nPurchase Date 2011-05-27 \nPurchase Cost 400000.00 \nDevelopment Cost 0.00 6,00,000\u00a0\u00a06\u00a0Lacs+", "dependent1": "Nil", "Sr No": "ii"}, "2": {"dependent2": "Nil", "dependent3": "Nil", "Description": "Commercial Buildings", "spouse": "Nil", "self": "Nil", "dependent1": "Nil", "Sr No": "iii"}, "3": {"dependent2": "Nil", "dependent3": "Nil", "Description": "Residential Buildings", "spouse": "Nil", "self": "Ranabaad Road, Chapra 39\nTotal Area 1417 sqft \nBuilt Up Area 373 sqft \nWhether Inherited N \nPurchase Date 2012-08-03 \nPurchase Cost 638771.00 \nDevelopment Cost 0.00 10,00,000\u00a0\u00a010\u00a0Lacs+", "dependent1": "Nil", "Sr No": "iv"}, "4": {"dependent2": "Nil", "dependent3": "Nil", "Description": "Others", "spouse": "Nil", "self": "Nil", "dependent1": "Nil", "Sr No": "v"}, "5": {"dependent2": "Nil", "dependent3": "Rs\u00a072,10,000 72\u00a0Lacs+", "Description": "72,10,000\u00a0\u00a072\u00a0Lacs+", "spouse": "Nil", "self": "Nil", "dependent1": "Nil", "Sr No": "Total Current Market Value of (i) to (v) (as per Affidavit)"}, "6": {"dependent2": "Nil", "dependent3": "Rs\u00a072,10,000 72\u00a0Lacs+", "Description": "Rs\u00a072,10,000 72\u00a0Lacs+", "spouse": "Nil", "self": "Nil", "dependent1": "Nil", "Sr No": "Totals Calculated"}}