{"0": {"dependent2": "Nil", "dependent1": "2,75,788\u00a0\u00a02\u00a0Lacs+", "self": "10,32,008\u00a0\u00a010\u00a0Lacs+", "dependent3": "Nil", "Description": "Gross Total Value (as per Affidavit)", "spouse": "7,95,708\u00a0\u00a07\u00a0Lacs+"}, "1": {"dependent2": "Nil", "dependent1": "Rs\u00a02,75,788 2\u00a0Lacs+", "self": "Rs\u00a010,32,008 10\u00a0Lacs+", "dependent3": "Nil", "Description": "Totals (Calculated as Sum of Values)", "spouse": "Rs\u00a07,95,708 7\u00a0Lacs+"}, "2": {"dependent2": "Nil", "dependent1": "Nil", "self": "15,000\u00a0\u00a015\u00a0Thou+", "dependent3": "Nil", "Description": "Cash", "spouse": "10,000\u00a0\u00a010\u00a0Thou+"}, "3": {"dependent2": "Nil", "dependent1": "SB A/c no. 20224796825 with SBI Midnapure Br.  24,788\u00a0\u00a024\u00a0Thou+", "self": "Bank of India Midnapore SB A/c no. 4310110100006347 as on 17.02.2016  1,58,190\u00a0\u00a01\u00a0Lacs+ Vidyasagar Central Cooperative Bank Ltd SB A/c no. 19072  4,083\u00a0\u00a04\u00a0Thou+ State Bank of India A/c no. 35630154160 as on 11.03.2016  10,000\u00a0\u00a010\u00a0Thou+", "dependent3": "Nil", "Description": "Deposits in Banks, Financial Institutions and Non-Banking Financial Companies", "spouse": "United Bank of India Khargapur SB A/c no. 017901211362  18,008\u00a0\u00a018\u00a0Thou+ State Bank of India Midnapore Mian Br. SB A/c no. 11161792115  10,200\u00a0\u00a010\u00a0Thou+ Term Deposit United Bank of India Midnapore Br. A/c no. 0179100262675  10,000\u00a0\u00a010\u00a0Thou+"}, "4": {"dependent2": "Nil", "dependent1": "Nil", "self": "Nil", "dependent3": "Nil", "Description": "Bonds, Debentures and Shares in companies", "spouse": "Nil"}, "5": {"dependent2": "Nil", "dependent1": "K.V.P. No. 53AB694911, Mid Court S.P.O. Dt.23.11.2005  1,000\u00a0\u00a01\u00a0Thou+", "self": "Mid HPO, MIS A/c no. 223195  15,000\u00a0\u00a015\u00a0Thou+ Mid HPO, MIS A/c no.223196  22,500\u00a0\u00a022\u00a0Thou+ Mid Court SPO  MIS A/c no.123133  1,50,000\u00a0\u00a01\u00a0Lacs+ Mid Court SPO  MIS A/c no.123755  93,000\u00a0\u00a093\u00a0Thou+ Mid Court SPO Postal Saving A/c no. 1284934  62,235\u00a0\u00a062\u00a0Thou+", "dependent3": "Nil", "Description": "(a) NSS, Postal Savings etc", "spouse": "NSC Natunbazar N.O.C. No.69CC874579, Dt. 24.09.2009  1,000\u00a0\u00a01\u00a0Thou+ NSC Natunbazar N.O.C. No.69CC512107, Dt. 30.01.2009  1,000\u00a0\u00a01\u00a0Thou+ NSC Natunbazar N.O.C. No.69CC512110, Dt. 27.08.2009  1,000\u00a0\u00a01\u00a0Thou+ NSC Natunbazar N.O.C. No.69CC512168, Dt. 30.01.2010  1,000\u00a0\u00a01\u00a0Thou+ NSC Natunbazar N.O.C. No.69CC512164, dt. 27.01.2010  1,000\u00a0\u00a01\u00a0Thou+ NSC Natunbazar N.O.C. No.69CC12197, dt. 26.03.2010  1,000\u00a0\u00a01\u00a0Thou+ NSC Natunbazar N.O.C. No.69CC512196, Dt. 26.03.2010  1,000\u00a0\u00a01\u00a0Thou+ NSC Natunbazar N.O.C. No.69CC512195, Dt. 26.03.2010  1,000\u00a0\u00a01\u00a0Thou+ NSC Natunbazar N.O.C. No.69CC512138, dt. 31.12.2009  1,000\u00a0\u00a01\u00a0Thou+ NSC Natunbazar N.O.C. No.69CC512118, Dt. 13.10.2009  1,000\u00a0\u00a01\u00a0Thou+ NSC Natunbazar N.O.C. No.61DD168165, Dt.04.03.2010  5,000\u00a0\u00a05\u00a0Thou+ NSC Natunbazar N.O.C. No.57DD177375, dt. 02.07.2008  5,000\u00a0\u00a05\u00a0Thou+ NSC Natunbazar N.O.C. No.61DD168161, Dt. 30.01.2010  5,000\u00a0\u00a05\u00a0Thou+ NSC Natunbazar N.O.C. No.90EE034250, Dt. 26.03.2010  10,000\u00a0\u00a010\u00a0Thou+ NSC Natunbazar N.O.C. No.90EE034249, Dt. 26.03.2010  10,000\u00a0\u00a010\u00a0Thou+ NSC Natunbazar N.O.C. No.74DD471923, Dt. 04.12.2012  5,000\u00a0\u00a05\u00a0Thou+ Mis A/c no. 223195, Mid H.P.O.   15,000\u00a0\u00a015\u00a0Thou+ Mis A/c no. 223196, Mis H.P.O.   22,500\u00a0\u00a022\u00a0Thou+"}, "6": {"dependent2": "Nil", "dependent1": "Policy No.43786020, Br. Howrah  1,00,000\u00a0\u00a01\u00a0Lacs+ Policy No.437860198, Br. Howrah  1,00,000\u00a0\u00a01\u00a0Lacs+ Policy No.431437714, Br. Mid  50,000\u00a0\u00a050\u00a0Thou+", "self": "Policy No.431757794 Br. Mid   52,000\u00a0\u00a052\u00a0Thou+ Policy No.436555702 Br. Mid  20,000\u00a0\u00a020\u00a0Thou+ Policy No.498558525 Br. Mid  4,00,000\u00a0\u00a04\u00a0Lacs+", "dependent3": "Nil", "Description": "(b)LIC or other insurance Policies", "spouse": "Policy No. 459630725, Br. K.G.P.  1,00,000\u00a0\u00a01\u00a0Lacs+ Policy No. 436602129, Br. Howrah  50,000\u00a0\u00a050\u00a0Thou+ Policy No. 459048637, Br. K.G.P.  2,00,000\u00a0\u00a02\u00a0Lacs+ Policy No. 499325460, Br. Mid   1,60,000\u00a0\u00a01\u00a0Lacs+"}, "7": {"dependent2": "Nil", "dependent1": "Nil", "self": "Nil", "dependent3": "Nil", "Description": "Personal loans/advance given", "spouse": "Nil"}, "8": {"dependent2": "Nil", "dependent1": "Nil", "self": "Nil", "dependent3": "Nil", "Description": "Motor Vehicles (details of make, etc.)", "spouse": "Nil"}, "9": {"dependent2": "Nil", "dependent1": "Nil", "self": "10gm  30,000\u00a0\u00a030\u00a0Thou+", "dependent3": "Nil", "Description": "Jewellery (give details weight value)", "spouse": "53gm  1,50,000\u00a0\u00a01\u00a0Lacs+"}, "10": {"dependent2": "Nil", "dependent1": "Nil", "self": "Nil", "dependent3": "Nil", "Description": "Other assets, such as values of claims / interests", "spouse": "Nil"}}