{"0": {"dependent2": "Nil", "dependent1": "Nil", "self": "44,00,000\u00a0\u00a044\u00a0Lacs+", "dependent3": "Nil", "Description": "Total Current Market Value of (i) to (v) (as per Affidavit)", "spouse": "90,00,000\u00a0\u00a090\u00a0Lacs+"}, "1": {"dependent2": "Nil", "dependent1": "Nil", "self": "Rs\u00a044,00,000 44\u00a0Lacs+", "dependent3": "Nil", "Description": "Totals Calculated", "spouse": "Rs\u00a090,00,000 90\u00a0Lacs+"}, "2": {"dependent2": "Nil", "dependent1": "Nil", "self": "Nil", "dependent3": "Nil", "Description": "Agricultural Land", "spouse": "Nil"}, "3": {"dependent2": "Nil", "dependent1": "Nil", "self": "Vill. & PO. Chougacha, Dist. Nadia, WB\nTotal Area 5040 sq. ft. \nBuilt Up Area  \nWhether Inherited N \nPurchase Date 2002-01-01 \nPurchase Cost 300000.00 \nDevelopment Cost 0.00 14,00,000\u00a0\u00a014\u00a0Lacs+", "dependent3": "Nil", "Description": "Non Agricultural Land", "spouse": "Nil"}, "4": {"dependent2": "Nil", "dependent1": "Nil", "self": "Nil", "dependent3": "Nil", "Description": "Commercial Buildings", "spouse": "Nil"}, "5": {"dependent2": "Nil", "dependent1": "Nil", "self": "Jyangra, Chowmatha, Rajarhat Road, Kolkata 700059\nTotal Area 820 Sq. ft. \nBuilt Up Area 720 sq. ft. \nWhether Inherited N \nPurchase Date 1996-01-01 \nPurchase Cost 400000.00 \nDevelopment Cost 0.00 30,00,000\u00a0\u00a030\u00a0Lacs+", "dependent3": "Nil", "Description": "Residential Buildings", "spouse": "Jyangra, Chowmatha, Rajarhat Road, Kolkata 700059\nTotal Area 3000 sq. ft. \nBuilt Up Area 3000 sq. ft. \nWhether Inherited N \nPurchase Date 1989-01-01 \nPurchase Cost 2000000.00 \nDevelopment Cost 0.00 90,00,000\u00a0\u00a090\u00a0Lacs+"}, "6": {"dependent2": "Nil", "dependent1": "Nil", "self": "Nil", "dependent3": "Nil", "Description": "Others", "spouse": "Nil"}}