{"0": {"Other Details / Other Acts / Sections Applicable": "147,  332,  427,  342", "IPC Sections Applicable": "1"}, "1": {"Other Details / Other Acts / Sections Applicable": "148,  149,  323,  516", "IPC Sections Applicable": "2"}, "2": {"Other Details / Other Acts / Sections Applicable": "143,  447,  427,  186,  353", "IPC Sections Applicable": "3"}, "3": {"Other Details / Other Acts / Sections Applicable": "147,  148,  149,  353,  323,  427,  435", "IPC Sections Applicable": "4"}, "4": {"Other Details / Other Acts / Sections Applicable": "143,  342,  352,  86,  353", "IPC Sections Applicable": "5"}, "5": {"Other Details / Other Acts / Sections Applicable": "Court taking Cognizance Ltd SDJM Asansol, Asansol GRPS 65/90, Date taking Cognizance 28.05.1990, NGR 816/2004, GDE No.1293/2014", "IPC Sections Applicable": "6"}, "6": {"Other Details / Other Acts / Sections Applicable": "143,  448,  427,  506", "IPC Sections Applicable": "7"}}