{"0": {"dependent2": "Nil", "dependent3": "Nil", "spouse": "0", "self": "0", "Description": "Gross Total Value (as per Affidavit)", "dependent1": "Nil"}, "1": {"dependent2": "Nil", "dependent3": "Nil", "spouse": "Rs\u00a02,000 2\u00a0Thou+", "self": "Rs\u00a01,27,400 1\u00a0Lacs+", "Description": "Totals (Calculated as Sum of Values)", "dependent1": "Nil"}, "2": {"dependent2": "Nil", "dependent3": "Nil", "spouse": "2,000\u00a0\u00a02\u00a0Thou+", "self": "10,000\u00a0\u00a010\u00a0Thou+", "Description": "Cash", "dependent1": "Nil"}, "3": {"dependent2": "Nil", "dependent3": "Nil", "spouse": "Nil", "self": "S.B.I. Keshiary Branch A/c no.20104223567  6,300\u00a0\u00a06\u00a0Thou+ PNB Keshiary A/c No.232200000143640  6,000\u00a0\u00a06\u00a0Thou+ UBI A/c no.0682010316781  5,100\u00a0\u00a05\u00a0Thou+", "Description": "Deposits in Banks, Financial Institutions and Non-Banking Financial Companies", "dependent1": "Nil"}, "4": {"dependent2": "Nil", "dependent3": "Nil", "spouse": "Nil", "self": "Nil", "Description": "Bonds, Debentures and Shares in companies", "dependent1": "Nil"}, "5": {"dependent2": "Nil", "dependent3": "Nil", "spouse": "Nil", "self": "Nil", "Description": "(a) NSS, Postal Savings etc", "dependent1": "Nil"}, "6": {"dependent2": "Nil", "dependent3": "Nil", "spouse": "Nil", "self": "LIC Policy No.759099996  1,00,000\u00a0\u00a01\u00a0Lacs+", "Description": "(b)LIC or other insurance Policies", "dependent1": "Nil"}, "7": {"dependent2": "Nil", "dependent3": "Nil", "spouse": "Nil", "self": "Nil", "Description": "Personal loans/advance given", "dependent1": "Nil"}, "8": {"dependent2": "Nil", "dependent3": "Nil", "spouse": "Nil", "self": "WB-34/AP-3670 M/C  0*(Value Not Given)", "Description": "Motor Vehicles (details of make, etc.)", "dependent1": "Nil"}, "9": {"dependent2": "Nil", "dependent3": "Nil", "spouse": "2 Bhoria  0*(Value Not Given)", "self": "Nil", "Description": "Jewellery (give details weight value)", "dependent1": "Nil"}, "10": {"dependent2": "Nil", "dependent3": "Nil", "spouse": "Nil", "self": "Nil", "Description": "Other assets, such as values of claims / interests", "dependent1": "Nil"}}