{"0": {"Description": "Total Current Market Value of (i) to (v) (as per Affidavit)", "self": "3,50,000\u00a0\u00a03\u00a0Lacs+", "spouse": "Nil", "dependent1": "Nil", "dependent2": "Nil", "dependent3": "Nil"}, "1": {"Description": "Totals Calculated", "self": "Rs\u00a03,50,000 3\u00a0Lacs+", "spouse": "Nil", "dependent1": "Nil", "dependent2": "Nil", "dependent3": "Nil"}, "2": {"Description": "Agricultural Land", "self": "Mouza Ruknopur,Kh No-6038,Dag No-7188\nTotal Area 55 Dec. \nBuilt Up Area  \nWhether Inherited N \nPurchase Date 1979-12-04 \nPurchase Cost 5000.00 \nDevelopment Cost 0.00 50,000\u00a0\u00a050\u00a0Thou+", "spouse": "Nil", "dependent1": "Nil", "dependent2": "Nil", "dependent3": "Nil"}, "3": {"Description": "Non Agricultural Land", "self": "Nil", "spouse": "Nil", "dependent1": "Nil", "dependent2": "Nil", "dependent3": "Nil"}, "4": {"Description": "Commercial Buildings", "self": "Nil", "spouse": "Nil", "dependent1": "Nil", "dependent2": "Nil", "dependent3": "Nil"}, "5": {"Description": "Residential Buildings", "self": "Mouja Harinarpur Kh No-2752,Dag No-668\nTotal Area 04 Dec. \nBuilt Up Area 1200 Sq.ft. \nWhether Inherited N \nPurchase Date 2010-07-12 \nPurchase Cost 42000.00 \nDevelopment Cost 200000.00 3,00,000\u00a0\u00a03\u00a0Lacs+", "spouse": "Nil", "dependent1": "Nil", "dependent2": "Nil", "dependent3": "Nil"}, "6": {"Description": "Others", "self": "Nil", "spouse": "Nil", "dependent1": "Nil", "dependent2": "Nil", "dependent3": "Nil"}}