{"0": {"Other Details / Other Acts / Sections Applicable": "341,  186", "IPC Sections Applicable": "1"}, "1": {"Other Details / Other Acts / Sections Applicable": "147,  149,  336,  186,  353,  379,  511", "IPC Sections Applicable": "2"}, "2": {"Other Details / Other Acts / Sections Applicable": "147,  149,  186,  353,  379", "IPC Sections Applicable": "3"}, "3": {"Other Details / Other Acts / Sections Applicable": "LD.ACJM Islampur G.R. No. 68(M)/87, Patna RPF/Kishan Case, U/S-174A/195B/145/147 RPF Act 2003", "IPC Sections Applicable": "4"}, "4": {"Other Details / Other Acts / Sections Applicable": "147,  148,  149,  323, 325,  427,  353", "IPC Sections Applicable": "5"}, "5": {"Other Details / Other Acts / Sections Applicable": "147,  323,  325,  427,  506", "IPC Sections Applicable": "6"}, "6": {"Other Details / Other Acts / Sections Applicable": "LD.ACJM Islampur G.R. No.36/02", "IPC Sections Applicable": "7"}, "7": {"Other Details / Other Acts / Sections Applicable": "LD.JM Islampur GR 80/80", "IPC Sections Applicable": "8"}}