{"0": {"dependent2": "Nil", "dependent1": "Nil", "self": "81,72,621\u00a0\u00a081\u00a0Lacs+", "dependent3": "Nil", "Description": "Gross Total Value (as per Affidavit)", "spouse": "51,64,084\u00a0\u00a051\u00a0Lacs+"}, "1": {"dependent2": "Nil", "dependent1": "Nil", "self": "Rs\u00a081,72,620.96 81\u00a0Lacs+", "dependent3": "Nil", "Description": "Totals (Calculated as Sum of Values)", "spouse": "Rs\u00a051,64,084.95 51\u00a0Lacs+"}, "2": {"dependent2": "Nil", "dependent1": "Nil", "self": "2,46,128\u00a0\u00a02\u00a0Lacs+", "dependent3": "Nil", "Description": "Cash", "spouse": "3,08,627\u00a0\u00a03\u00a0Lacs+"}, "3": {"dependent2": "Nil", "dependent1": "Nil", "self": "SAVING BANK A/C WITH SBI RAMPURHAT BRANCH A/C NO.01190005815  66,790.68\u00a0\u00a066\u00a0Thou+ PPF A/C WITH SBI RAMPURHAT BRANCH A/C NO.11282219519  10,60,222.93\u00a0\u00a010\u00a0Lacs+ SAVING BANK A/C WITH SBI SURI BRANCH A/C NO.01190006322  65,262.12\u00a0\u00a065\u00a0Thou+ SAVING BANK A/C WITH SBI RAMPURHAT BRANCH A/C NO.11282152358  3,11,502\u00a0\u00a03\u00a0Lacs+ SAVING BANK A/C WITH BOB RAMPURHAT BRANCH A/C NO.36620100005537  1,63,438.17\u00a0\u00a01\u00a0Lacs+ SAVING BANK A/C WITH UBI RAMPURHAT BRANCH A/C 0212010093041  9,33,833.06\u00a0\u00a09\u00a0Lacs+", "dependent3": "Nil", "Description": "Deposits in Banks, Financial Institutions and Non-Banking Financial Companies", "spouse": "PPF BALANCE WITH SBI RAMPURHAT BRANCH A/C NO.11282221798  9,77,536.95\u00a0\u00a09\u00a0Lacs+ SAVING BANK A/C WITH UBI RAMPURHAT BRANCH A/C N.0212010096547  5,25,347\u00a0\u00a05\u00a0Lacs+ CURRENT A/C OF ASHA NURSING HOME PROP MINAKSHI CHATTERJEE  PBGB RAMPURHAT BRANCH A/C NO.0670200000050  7,604\u00a0\u00a07\u00a0Thou+ CURRENT ACCOUNT OF ASHA NURSING HOME PROP MINAKSHI CHATERJEE SBI RAMPURHAT BRANCH A/C NO.31921138705  6,00,372\u00a0\u00a06\u00a0Lacs+"}, "4": {"dependent2": "Nil", "dependent1": "Nil", "self": "MUTUL FUND WITH SBI FOLIO NO.211063917 50000 UNIT  5,00,000\u00a0\u00a05\u00a0Lacs+", "dependent3": "Nil", "Description": "Bonds, Debentures and Shares in companies", "spouse": "MUTUL FUND WITH SBI FOLIO NO.14090132  50000 UNIT  5,00,000\u00a0\u00a05\u00a0Lacs+"}, "5": {"dependent2": "Nil", "dependent1": "Nil", "self": "RD WITH POST OFFICE A/C NO.373285  1,70,000\u00a0\u00a01\u00a0Lacs+", "dependent3": "Nil", "Description": "(a) NSS, Postal Savings etc", "spouse": "RD WITH POST OFFICE A/C NO.177947  44,000\u00a0\u00a044\u00a0Thou+ RD WITH POST OFFICE A/C NO.178111  60,000\u00a0\u00a060\u00a0Thou+ RD WITH POST OFFICE A/C NO.178163  1,80,000\u00a0\u00a01\u00a0Lacs+"}, "6": {"dependent2": "Nil", "dependent1": "Nil", "self": "INVESTMENT IN LICI  14,58,094\u00a0\u00a014\u00a0Lacs+", "dependent3": "Nil", "Description": "(b)LIC or other insurance Policies", "spouse": "INVESTMENT IN LICI  7,02,467\u00a0\u00a07\u00a0Lacs+"}, "7": {"dependent2": "Nil", "dependent1": "Nil", "self": "Nil", "dependent3": "Nil", "Description": "Personal loans/advance given", "spouse": "Nil"}, "8": {"dependent2": "Nil", "dependent1": "Nil", "self": "TOYOTA MOTOR PURCHASED ON 21-01-15  24,33,138\u00a0\u00a024\u00a0Lacs+ MOTOR CAR   2,26,712\u00a0\u00a02\u00a0Lacs+", "dependent3": "Nil", "Description": "Motor Vehicles (details of make, etc.)", "spouse": "MARUTI SUZUKI AMBULANCE PURCHASED ON 15/07/2015  3,08,131\u00a0\u00a03\u00a0Lacs+"}, "9": {"dependent2": "Nil", "dependent1": "Nil", "self": "215 GM.  5,37,500\u00a0\u00a05\u00a0Lacs+", "dependent3": "Nil", "Description": "Jewellery (give details weight value)", "spouse": "380 GM  9,50,000\u00a0\u00a09\u00a0Lacs+"}, "10": {"dependent2": "Nil", "dependent1": "Nil", "self": "Nil", "dependent3": "Nil", "Description": "Other assets, such as values of claims / interests", "spouse": "Nil"}}