{"0": {"Description": "Total Current Market Value of (i) to (v) (as per Affidavit)", "self": "30,80,000\u00a0\u00a030\u00a0Lacs+", "spouse": "6,50,000\u00a0\u00a06\u00a0Lacs+", "dependent1": "Nil", "dependent2": "Nil", "dependent3": "Nil"}, "1": {"Description": "Totals Calculated", "self": "Rs\u00a030,80,000 30\u00a0Lacs+", "spouse": "Rs\u00a06,50,000 6\u00a0Lacs+", "dependent1": "Nil", "dependent2": "Nil", "dependent3": "Nil"}, "2": {"Description": "Agricultural Land", "self": "Mouza-Belhati, J.L. no. 48 PS- Nanur khatian No. 161, 245, 249, 258, 257, 163, 316, 110, 269\r\nDag nos. 1578, 1169, 1725, 2796, 1088, 1024, 1009, 1081, 1726, 1648, 1732, 1577, 1027, 3266\nTotal Area 2.86acres \nBuilt Up Area  \nWhether Inherited Y \nPurchase Date 0000-00-00 \nPurchase Cost 0.00 \nDevelopment Cost 0.00 8,70,000\u00a0\u00a08\u00a0Lacs+", "spouse": "Mouza-Binuria, PS-Bolpur, J.L. no. 54, Khatian no. 691 Dag no. 4660\nTotal Area 0.11decimal \nBuilt Up Area  \nWhether Inherited N \nPurchase Date 1992-06-03 \nPurchase Cost 4000.00 \nDevelopment Cost 0.00 1,50,000\u00a0\u00a01\u00a0Lacs+", "dependent1": "Nil", "dependent2": "Nil", "dependent3": "Nil"}, "3": {"Description": "Non Agricultural Land", "self": "Mouza-Belhati J.L. no. 48 PS-Nanur, Khatian nos. 245, 249, 326\r\nDag nos. 1155, 1549, 1132/3318, Area a) 5192 Sq. ft.(Bastu), b) 1.38 Acre (Pond)\nTotal Area  \nBuilt Up Area  \nWhether Inherited Y \nPurchase Date 0000-00-00 \nPurchase Cost 0.00 \nDevelopment Cost 0.00 4,10,000\u00a0\u00a04\u00a0Lacs+", "spouse": "Mouza-Bolpur, J.L. No. 99,Khatian nos. 3528, 3639 Dag no. 1167/3027, 388/10396, Date of Purchase 12.08.2002 & 16.08.2006\nTotal Area 2522.5sq.ft. \nBuilt Up Area  \nWhether Inherited N \nPurchase Date 2006-08-16 \nPurchase Cost 141650.00 \nDevelopment Cost 0.00 5,00,000\u00a0\u00a05\u00a0Lacs+", "dependent1": "Nil", "dependent2": "Nil", "dependent3": "Nil"}, "4": {"Description": "Commercial Buildings", "self": "Total Area  \nBuilt Up Area  \nWhether Inherited Y \nPurchase Date 0000-00-00 \nPurchase Cost 0.00 \nDevelopment Cost 0.00 3,00,000\u00a0\u00a03\u00a0Lacs+", "spouse": "Nil", "dependent1": "Nil", "dependent2": "Nil", "dependent3": "Nil"}, "5": {"Description": "Residential Buildings", "self": "Mouza-Bolpur, J.L. no. 99\nTotal Area 1423.5 Sq. ft. \nBuilt Up Area 1767sq.ft. \nWhether Inherited N \nPurchase Date 2002-10-23 \nPurchase Cost 66650.00 \nDevelopment Cost 1010000.00 15,00,000\u00a0\u00a015\u00a0Lacs+", "spouse": "Nil", "dependent1": "Nil", "dependent2": "Nil", "dependent3": "Nil"}, "6": {"Description": "Others", "self": "Nil", "spouse": "Nil", "dependent1": "Nil", "dependent2": "Nil", "dependent3": "Nil"}}