{"0": {"Description": "Agricultural Land", "self": "Nil", "spouse": "Nil", "dependent1": "Nil", "dependent2": "Nil", "dependent3": "Nil"}, "1": {"Description": "Non Agricultural Land", "self": "Nil", "spouse": "Nil", "dependent1": "Nil", "dependent2": "Nil", "dependent3": "Nil"}, "2": {"Description": "Commercial Buildings", "self": "Nil", "spouse": "Nil", "dependent1": "Nil", "dependent2": "Nil", "dependent3": "Nil"}, "3": {"Description": "Residential Buildings", "self": "1373, Chak Garia\r\nPS.-Purba Jadavpur, Kolkata\nTotal Area 1300 Sq.ft. \nBuilt Up Area 1300 Sq.ft. \nWhether Inherited N \nPurchase Date 2013-03-21 \nPurchase Cost 5300000.00 \nDevelopment Cost 0.00 53,00,000\u00a0\u00a053\u00a0Lacs+", "spouse": "Flat-4C, Gold Gardens, H/2, CIT Scheme No.118\nTotal Area 755 Sq.ft. \nBuilt Up Area 755 Sq.ft. \nWhether Inherited N \nPurchase Date 2003-09-04 \nPurchase Cost 685780.00 \nDevelopment Cost 0.00 35,00,000\u00a0\u00a035\u00a0Lacs+", "dependent1": "Nil", "dependent2": "Nil", "dependent3": "Nil"}, "4": {"Description": "Others", "self": "Nil", "spouse": "Nil", "dependent1": "Nil", "dependent2": "Nil", "dependent3": "Nil"}, "5": {"Description": "Total Current Market Value of (i) to (v) (as per Affidavit)", "self": "53,00,000\u00a0\u00a053\u00a0Lacs+", "spouse": "35,00,000\u00a0\u00a035\u00a0Lacs+", "dependent1": "Nil", "dependent2": "Nil", "dependent3": "Nil"}, "6": {"Description": "Totals Calculated", "self": "Rs\u00a053,00,000 53\u00a0Lacs+", "spouse": "Rs\u00a035,00,000 35\u00a0Lacs+", "dependent1": "Nil", "dependent2": "Nil", "dependent3": "Nil"}}