{"0": {"Description": "Gross Total Value (as per Affidavit)", "self": "10,45,927\u00a0\u00a010\u00a0Lacs+", "spouse": "4,04,465\u00a0\u00a04\u00a0Lacs+", "dependent1": "Nil", "dependent2": "Nil", "dependent3": "Nil"}, "1": {"Description": "Totals (Calculated as Sum of Values)", "self": "Rs\u00a010,48,433 10\u00a0Lacs+", "spouse": "Rs\u00a04,04,465 4\u00a0Lacs+", "dependent1": "Nil", "dependent2": "Nil", "dependent3": "Nil"}, "2": {"Description": "Cash", "self": "26,666\u00a0\u00a026\u00a0Thou+", "spouse": "37,387\u00a0\u00a037\u00a0Thou+", "dependent1": "Nil", "dependent2": "Nil", "dependent3": "Nil"}, "3": {"Description": "Deposits in Banks, Financial Institutions and Non-Banking Financial Companies", "self": "MIS   1,00,000\u00a0\u00a01\u00a0Lacs+ BANK OF BRODA  5,582\u00a0\u00a05\u00a0Thou+ E&NE RLY.COOP BANK   28,342\u00a0\u00a028\u00a0Thou+ SBI   9,483\u00a0\u00a09\u00a0Thou+", "spouse": "BANK OF BRODA   1,01,078\u00a0\u00a01\u00a0Lacs+ ORIENTAL OF COMMERCE  6,000\u00a0\u00a06\u00a0Thou+ RLY CO-OP BANK   35,000\u00a0\u00a035\u00a0Thou+", "dependent1": "Nil", "dependent2": "Nil", "dependent3": "Nil"}, "4": {"Description": "Bonds, Debentures and Shares in companies", "self": "SBI EQ.SHARE   5,000\u00a0\u00a05\u00a0Thou+ GRAPCO MINING  1,500\u00a0\u00a01\u00a0Thou+ MAGIC PRINTER  8,34,354\u00a0\u00a08\u00a0Lacs+", "spouse": "Nil", "dependent1": "Nil", "dependent2": "Nil", "dependent3": "Nil"}, "5": {"Description": "(a) NSS, Postal Savings etc", "self": "Nil", "spouse": "Nil", "dependent1": "Nil", "dependent2": "Nil", "dependent3": "Nil"}, "6": {"Description": "LIC PREMIUM  2,506\u00a0\u00a02\u00a0Thou+", "self": "Nil", "spouse": "Nil", "dependent1": "Nil", "dependent2": "Nil", "dependent3": "Rs\u00a02,506 2\u00a0Thou+"}, "7": {"Description": "Personal loans/advance given", "self": "35,000\u00a0\u00a035\u00a0Thou+", "spouse": "Nil", "dependent1": "Nil", "dependent2": "Nil", "dependent3": "Nil"}, "8": {"Description": "Motor Vehicles (details of make, etc.)", "self": "Nil", "spouse": "Nil", "dependent1": "Nil", "dependent2": "Nil", "dependent3": "Nil"}, "9": {"Description": "Jewellery (give details weight value)", "self": "Nil", "spouse": "75 GRM ORNAMENT FOR  2,25,000\u00a0\u00a02\u00a0Lacs+", "dependent1": "Nil", "dependent2": "Nil", "dependent3": "Nil"}, "10": {"Description": "Other assets, such as values of claims / interests", "self": "Nil", "spouse": "Nil", "dependent1": "Nil", "dependent2": "Nil", "dependent3": "Nil"}}