{"0": {"Candidate": "DR. MRIGANKA MAHATO", "Votes": "468277", "Party": "All India Trinamool Congress"}, "1": {"Candidate": "NARAHARI  MAHATO", "Votes": "314400", "Party": "All India Forward Bloc"}, "2": {"Candidate": "NEPAL MAHATA", "Votes": "257923", "Party": "Indian National Congress"}, "3": {"Candidate": "BIKASH BANERJEE", "Votes": "86236", "Party": "Bharatiya Janata Party"}, "4": {"Candidate": "SUBARNA  KUMAR", "Votes": "11266", "Party": "SOCIALIST UNITY CENTRE OF INDIA (COMMUNIST)"}, "5": {"Candidate": "MIHIR KUMAR RAJWAR", "Votes": "9850", "Party": "Bahujan Samaj Party"}, "6": {"Candidate": "AJIT PRASAD MAHATA", "Votes": "9012", "Party": "Jharkhand Vikas Morcha (Prajatantrik)"}, "7": {"Candidate": "TAPAN KUMAR MAHATO", "Votes": "7386", "Party": "Jharkhand Mukti Morcha"}, "8": {"Candidate": "BAIDYANATH HANSDA", "Votes": "7168", "Party": "Jharkhand Disom Party"}, "9": {"Candidate": "MONBODH MAHATO", "Votes": "6774", "Party": "Independent"}, "10": {"Candidate": "DHIREN RAJAK", "Votes": "5584", "Party": "Independent"}, "11": {"Candidate": "PURNA CHANDRA TUDU", "Votes": "4073", "Party": "Independent"}, "12": {"Candidate": "None of the Above", "Votes": "16726", "Party": "None of the Above"}}