{"0": {}, "1": {"Candidate": {"data": "Mausam Noor\u00a0\u00a0 Winner", "url": "http://www.myneta.info/ls2014/candidate.php?candidate_id=4370"}, "Party": "INC", "Criminal Cases": "0", "Education": "Graduate Professional", "Age": "34", "Total Assets": "Rs\u00a097,78,222 ~ 97\u00a0Lacs+", "Liabilities": "Rs\u00a028,534 ~ 28\u00a0Thou+"}, "2": {"Candidate": {"data": "Abdul Khaleque", "url": "http://www.myneta.info/ls2014/candidate.php?candidate_id=4847"}, "Party": "AIUDF", "Criminal Cases": "0", "Education": "Graduate", "Age": "46", "Total Assets": "Rs\u00a043,67,584 ~ 43\u00a0Lacs+", "Liabilities": "Rs\u00a09,80,000 ~ 9\u00a0Lacs+"}, "3": {"Candidate": {"data": "Bishnu Pada Barman", "url": "http://www.myneta.info/ls2014/candidate.php?candidate_id=4845"}, "Party": "Amra Bangalee", "Criminal Cases": "0", "Education": "Graduate", "Age": "48", "Total Assets": "Rs\u00a010,05,000 ~ 10\u00a0Lacs+", "Liabilities": "Rs\u00a02,60,000 ~ 2\u00a0Lacs+"}, "4": {"Candidate": {"data": "Chitta Ranjan Kirttania", "url": "http://www.myneta.info/ls2014/candidate.php?candidate_id=4371"}, "Party": "BSP", "Criminal Cases": "0", "Education": "Graduate", "Age": "65", "Total Assets": "Rs\u00a01,76,60,906 ~ 1\u00a0Crore+", "Liabilities": "Rs\u00a08,40,000 ~ 8\u00a0Lacs+"}, "5": {"Candidate": {"data": "Gautam Sarkar", "url": "http://www.myneta.info/ls2014/candidate.php?candidate_id=4367"}, "Party": "SUCI(C)", "Criminal Cases": "0", "Education": "Post Graduate", "Age": "37", "Total Assets": "Rs\u00a03,27,400 ~ 3\u00a0Lacs+", "Liabilities": "Rs\u00a00 ~"}, "6": {"Candidate": {"data": "Imanuyel Hemram", "url": "http://www.myneta.info/ls2014/candidate.php?candidate_id=4368"}, "Party": "Jharkhand Disom Party", "Criminal Cases": "0", "Education": "10th Pass", "Age": "33", "Total Assets": "Rs\u00a064,000 ~ 64\u00a0Thou+", "Liabilities": "Rs\u00a00 ~"}, "7": {"Candidate": {"data": "Khagen Murmu", "url": "http://www.myneta.info/ls2014/candidate.php?candidate_id=4366"}, "Party": "CPI(M)", "Criminal Cases": "0", "Education": "Graduate", "Age": "59", "Total Assets": "Rs\u00a053,42,394 ~ 53\u00a0Lacs+", "Liabilities": "Rs\u00a02,91,761 ~ 2\u00a0Lacs+"}, "8": {"Candidate": {"data": "Md. Nurul Islam", "url": "http://www.myneta.info/ls2014/candidate.php?candidate_id=3825"}, "Party": "Welfare Party Of India", "Criminal Cases": "0", "Education": "Graduate Professional", "Age": "56", "Total Assets": "Rs\u00a01,21,48,752 ~ 1\u00a0Crore+", "Liabilities": "Rs\u00a00 ~"}, "9": {"Candidate": {"data": "Milan Das", "url": "http://www.myneta.info/ls2014/candidate.php?candidate_id=4846"}, "Party": "SP", "Criminal Cases": "0", "Education": "12th Pass", "Age": "52", "Total Assets": "Rs\u00a055,02,108 ~ 55\u00a0Lacs+", "Liabilities": "Rs\u00a012,01,557 ~ 12\u00a0Lacs+"}, "10": {"Candidate": {"data": "Minara Khatun", "url": "http://www.myneta.info/ls2014/candidate.php?candidate_id=4372"}, "Party": "Hindustan Krantikari Dal", "Criminal Cases": "0", "Education": "10th Pass", "Age": "32", "Total Assets": "Rs\u00a011,72,926 ~ 11\u00a0Lacs+", "Liabilities": "Rs\u00a00 ~"}, "11": {"Candidate": {"data": "Monatan Hembram", "url": "http://www.myneta.info/ls2014/candidate.php?candidate_id=4373"}, "Party": "Bahujan Mukti Party", "Criminal Cases": "0", "Education": "Graduate", "Age": "29", "Total Assets": "Rs\u00a048,000 ~ 48\u00a0Thou+", "Liabilities": "Rs\u00a00 ~"}, "12": {"Candidate": {"data": "Soumitra Ray", "url": "http://www.myneta.info/ls2014/candidate.php?candidate_id=4369"}, "Party": "AITC", "Criminal Cases": "0", "Education": "Graduate", "Age": "54", "Total Assets": "Rs\u00a055,16,468 ~ 55\u00a0Lacs+", "Liabilities": "Rs\u00a00 ~"}, "13": {"Candidate": {"data": "Subhash Krishna Goswami", "url": "http://www.myneta.info/ls2014/candidate.php?candidate_id=4848"}, "Party": "BJP", "Criminal Cases": "0", "Education": "12th Pass", "Age": "69", "Total Assets": "Rs\u00a022,36,912 ~ 22\u00a0Lacs+", "Liabilities": "Rs\u00a00 ~"}, "14": {"Candidate": {"data": "Suren Murmu", "url": "http://www.myneta.info/ls2014/candidate.php?candidate_id=4844"}, "Party": "IND", "Criminal Cases": "0", "Education": "8th Pass", "Age": "40", "Total Assets": "Rs\u00a05,33,000 ~ 5\u00a0Lacs+", "Liabilities": "Rs\u00a00 ~"}}